simple_common/__init__.py
simple_common/local/__init__.py
simple_common/local/local_object.py
simple_common/mysql_utils/__init__.py
simple_common/service/__init__.py
simple_common/service/basic.py
simple_common/service/resp.py
simple_common/utils/__init__.py
simple_common/utils/basic.py
simple_common/utils/cmd.py
simple_common/utils/collections.py
simple_common/utils/date.py
simple_common/utils/dns_utils.py
simple_common/utils/file.py
simple_common/utils/log.py
simple_common/utils/redis_util.py
simple_common/utils/string_utils.py
simple_common/utils/thread.py
simple_common/utils/xdict.py
simple_common-0.0.1.dist-info/LICENSE
simple_common-0.0.1.dist-info/METADATA
simple_common-0.0.1.dist-info/WHEEL
simple_common-0.0.1.dist-info/top_level.txt
simple_common-0.0.1.dist-info/RECORD
